{
  "patient_id": "PID000001",
  "timepoint": 1,
  "study_date": "2023-08-12",
  "recist": {
    "baseline_sld_mm": 96,
    "current_sld_mm": 61,
    "nadir_sld_mm": 61,
    "overall_response": "PR"
  },
  "complexity_profile": {
    "level": 2,
    "level_name": "C2",
    "artifact": {
      "key": "beam_hardening",
      "impact": 2,
      "report_phrase": "Beam-hardening streak artifact from dense structures limits evaluation.",
      "severity_rank": 3
    }
  },
  "staging_relevance": 4.0,
  "extras": {
    "incidentals": [
      {
        "organ": "aorta_great_vessels",
        "text": "tortuosity"
      }
    ],
    "negatives": [
      {
        "organ": "mesentery_peritoneum",
        "text": "no peritoneal nodularity"
      },
      {
        "organ": "spleen",
        "text": "spleen normal size"
      },
      {
        "organ": "pancreas",
        "text": "pancreas is normal"
      },
      {
        "organ": "gi",
        "text": "no colonic mass"
      },
      {
        "organ": "aorta_great_vessels",
        "text": "aorta normal caliber"
      }
    ],
    "post_treatment": [],
    "lesions": [
      {
        "lesion_id": "primary:kidney",
        "kind": "primary",
        "organ": "kidney",
        "location": "left kidney, interpolar",
        "rule": "longest",
        "baseline_mm": 48,
        "follow_mm": 31,
        "size_mm_current": 31,
        "margin": "spiculated",
        "enhancement": "hyperenhancing",
        "suspicious": true,
        "target": true
      },
      {
        "lesion_id": "ln:mesenteric",
        "kind": "ln",
        "organ": "lymph",
        "station": "mesenteric",
        "rule": "short_axis",
        "baseline_mm": 27,
        "follow_mm": 17,
        "size_mm_current": 17,
        "necrosis": false,
        "suspicious": true,
        "target": true
      },
      {
        "lesion_id": "met:peritoneum",
        "kind": "met",
        "organ": "peritoneum",
        "rule": "longest",
        "baseline_mm": 21,
        "follow_mm": 13,
        "size_mm_current": 13,
        "suspicious": true,
        "target": true
      }
    ]
  }
}